README.rst
setup.py
poetri/__init__.py
poetri/generate_jwk_private.py
poetri/generate_jwk_public.py
poetri/sign_jwk.py
poetri/verify_jws_with_jwk.py
poetri/verify_jws_with_jwk_url.py
poetri/verify_poet.py
poetri.egg-info/PKG-INFO
poetri.egg-info/SOURCES.txt
poetri.egg-info/dependency_links.txt
poetri.egg-info/requires.txt
poetri.egg-info/top_level.txt
tests/__init__.py
tests/test_key_generation.py
tests/test_sign_and_verify.py